ordeq_networkx/__init__.py
ordeq_networkx/_version.py
ordeq_networkx/networkx_gml.py
ordeq_networkx/networkx_graphml.py
ordeq_networkx/networkx_json.py
ordeq_networkx-1.0.0.dist-info/licenses/LICENSE
ordeq_networkx-1.0.0.dist-info/METADATA
ordeq_networkx-1.0.0.dist-info/WHEEL
ordeq_networkx-1.0.0.dist-info/top_level.txt
ordeq_networkx-1.0.0.dist-info/RECORD
